LICENSE
MANIFEST.in
README.rst
requirements.txt
setup.py
docs/Makefile
docs/api.rst
docs/conf.py
docs/description.rst
docs/examples.rst
docs/index.rst
docs/installation.rst
docs/overview.rst
docs/requirements.txt
docs/_static/banner.svg
docs/_static/favicon.ico
docs/_static/logo.png
docs/notebooks/doublesersic.ipynb
docs/notebooks/tutorial.ipynb
statmorph/__init__.py
statmorph/statmorph.py
statmorph/statmorph_asym_symmetric_mask.py
statmorph.egg-info/PKG-INFO
statmorph.egg-info/SOURCES.txt
statmorph.egg-info/dependency_links.txt
statmorph.egg-info/requires.txt
statmorph.egg-info/top_level.txt
statmorph/tests/__init__.py
statmorph/tests/test_statmorph.py
statmorph/tests/data/slice.fits
statmorph/utils/__init__.py
statmorph/utils/image_diagnostics.py
statmorph/utils/tests/test_image_diagnostics.py