Metadata-Version: 2.1
Name: statmorph
Version: 0.6.1
Summary: Non-parametric morphological diagnostics of galaxy images
Home-page: https://github.com/vrodgom/statmorph
Author: Vicente Rodriguez-Gomez
Author-email: vrodgom.astro@gmail.com
License: BSD
Keywords: astronomy galaxies galaxy-morphology non-parametric
Classifier: Development Status :: 4 - Beta
Classifier: Intended Audience :: Science/Research
Classifier: License :: OSI Approved :: BSD License
Classifier: Programming Language :: Python
Classifier: Programming Language :: Python :: 3
Classifier: Topic :: Scientific/Engineering :: Astronomy
Requires-Python: >=3.9
License-File: LICENSE
Requires-Dist: numpy>=1.14.0
Requires-Dist: scipy>=0.19
Requires-Dist: scikit-image>=0.25.0
Requires-Dist: astropy>=2.0
Requires-Dist: photutils>=0.7
Provides-Extra: matplotlib
Requires-Dist: matplotlib>=3.0; extra == "matplotlib"
